README.rst
setup.py
./__init__.py
./application.py
./chat.py
./tryton.cfg
./tests/__init__.py
./tests/test_chat.py
openlabs_nereid_chat.egg-info/PKG-INFO
openlabs_nereid_chat.egg-info/SOURCES.txt
openlabs_nereid_chat.egg-info/dependency_links.txt
openlabs_nereid_chat.egg-info/entry_points.txt
openlabs_nereid_chat.egg-info/not-zip-safe
openlabs_nereid_chat.egg-info/requires.txt
openlabs_nereid_chat.egg-info/top_level.txt