Metadata-Version: 1.1
Name: openlabs-nereid-chat
Version: 3.0.1.1
Summary: Nereid Chat module
Home-page: http://www.openlabs.co.in/
Author: Openlabs Technologies & Consulting (P) LTD
Author-email: info@openlabs.co.in
License: GPL-3
Platform: UNKNOWN
Classifier: Development Status :: 4 - Beta
Classifier: Environment :: Plugins
Classifier: Intended Audience :: Developers
Classifier: License :: OSI Approved :: GNU General Public License (GPL)
Classifier: Natural Language :: English
Classifier: Operating System :: OS Independent
Classifier: Programming Language :: Python
Classifier: Topic :: Office/Business
